[
    {
        "nome": "leo",
        "senha": "leo123456",
        "cep": "76914-754",
        "rua": "Rua Ita\u00fana",
        "numero": 717,
        "tentativas": 1,
        "recompensa": 0
    },
    {
        "nome": "gabriella",
        "senha": "gabi123",
        "cep": "22640-060",
        "rua": "Avenida Grande Canal",
        "numero": 33,
        "tentativas": 0,
        "recompensa": 0
    },
    {
        "nome": "adenor",
        "senha": "tite123",
        "cep": "96083-050",
        "rua": "Rua Cidade de Barcelos",
        "numero": 32,
        "tentativas": 3,
        "recompensa": 0
    },
    {
        "nome": "ana",
        "senha": "aninha",
        "cep": "64009-125",
        "rua": "Rua Manoel Marques Furtado",
        "numero": 384,
        "tentativas": 3,
        "recompensa": 0
    },
    {
        "nome": "leozinho",
        "senha": "123456",
        "cep": "59612-150",
        "rua": "Rua Luiz Ludugero",
        "numero": 670,
        "tentativas": 3,
        "recompensa": 0
    },
    {
        "nome": "lucas",
        "senha": "lucastri",
        "cep": "65055-430",
        "rua": "Travessa da Pedreira",
        "numero": 3,
        "tentativas": 3,
        "recompensa": 0
    },
    {
        "nome": "luiza",
        "senha": "lulu123",
        "cep": "35162-335",
        "rua": "Rua Mandacaru",
        "numero": 763,
        "tentativas": 3,
        "recompensa": 0
    },
    {
        "nome": "andrea",
        "senha": "andreamoreira",
        "cep": "57606-070",
        "rua": "Rua Jos\u00e9 Ferreira do Nascimento",
        "numero": 73,
        "tentativas": 3,
        "recompensa": 0
    },
    {
        "nome": "luiz",
        "senha": "123luiz",
        "cep": "29163-392",
        "rua": "Avenida Carapebus",
        "numero": 52,
        "tentativas": 3,
        "recompensa": 0
    },
    {
        "nome": "joao",
        "senha": "joao123",
        "cep": "65072-870",
        "rua": "Rua Ros\u00e1rio",
        "numero": 34,
        "tentativas": 3,
        "recompensa": 0
    },
    {
        "nome": "mauro",
        "senha": "maumau123",
        "cep": "81590-500",
        "rua": "Rua Nicodemus Zeglin",
        "numero": 12,
        "tentativas": 0,
        "recompensa": 1
    },
    {
        "nome": "lindaflor",
        "senha": "lindaflor1234",
        "cep": "64013-591",
        "rua": "Quadra 138",
        "numero": 32,
        "tentativas": 2,
        "recompensa": 1
    },
    {
        "nome": "luara",
        "senha": "lua123",
        "cep": "03422-000",
        "rua": "Avenida Guilherme Giorgi",
        "numero": 21,
        "tentativas": 3,
        "recompensa": 0
    },
    {
        "nome": "andersson",
        "senha": "daronco",
        "cep": "05281-110",
        "rua": "Rua Lima Barreto",
        "numero": 45,
        "tentativas": 3,
        "recompensa": 0
    },
    {
        "nome": "lurdes",
        "senha": "lurdes123",
        "cep": "02258-260",
        "rua": "Rua Major Vital Bandeira de Melo",
        "numero": 3001,
        "tentativas": 3,
        "recompensa": 0
    },
    {
        "nome": "lula",
        "senha": "kadrao",
        "cep": "03407-045",
        "rua": "Viela Manoel Gon\u00e7alez Alhilla",
        "numero": 123,
        "tentativas": 3,
        "recompensa": 0
    },
    {
        "nome": "eduardo",
        "senha": "dudu123",
        "cep": "05892-350",
        "rua": "Rua C\u00e9sar Bierrenbach",
        "numero": 23,
        "tentativas": 3,
        "recompensa": 0
    },
    {
        "nome": "jhony",
        "senha": "jhonjhon",
        "cep": "03361-010",
        "rua": "Avenida Cipriano Rodrigues",
        "numero": 210,
        "tentativas": 2,
        "recompensa": 0
    }
]